inotify_service/__init__.py
inotify_service/command.py
inotify_service/handler.py
inotify_service/log.py
inotify_service/service.py
inotify_service-1.0.2.dist-info/LICENSE.txt
inotify_service-1.0.2.dist-info/METADATA
inotify_service-1.0.2.dist-info/WHEEL
inotify_service-1.0.2.dist-info/entry_points.txt
inotify_service-1.0.2.dist-info/top_level.txt
inotify_service-1.0.2.dist-info/zip-safe
inotify_service-1.0.2.dist-info/RECORD
