Metadata-Version: 2.1
Name: inotify-service
Version: 1.0.2
Summary: Run scripts responding to inotify events
Home-page: https://github.com/majerteam/inotify_service
Author: Gaston Tjebbes
Author-email: g.t@majerti.fr
License: GPLv3
Keywords: inotify incron asyncio
Platform: UNKNOWN
Classifier: License :: OSI Approved :: GNU General Public License v3 (GPLv3)
Classifier: Programming Language :: Python
Classifier: Operating System :: Unix
Requires-Python: >=3.6
License-File: LICENSE.txt
Requires-Dist: asyncinotify
Requires-Dist: pyyaml
